{"branch_id":"8bdd1922-8a9f-4c6b-b94c-15fa7b33d9e0","name":"title","settings":{"physics":{"gravity":[0,-9.8,0]},"render":{"fog_end":1000,"fog_start":1,"global_ambient":[0.2,0.2,0.2],"fog_color":[0,0,0],"fog":"none","fog_density":0.01,"gamma_correction":1,"tonemapping":0,"exposure":1,"skybox":null,"skyboxIntensity":1,"skyboxRotation":[0,0,0],"skyboxMip":0,"lightmapSizeMultiplier":16,"lightmapMaxResolution":2048,"lightmapMode":1,"lightmapFilterEnabled":false,"lightmapFilterRange":10,"lightmapFilterSmoothness":0.2,"ambientBake":false,"ambientBakeNumSamples":1,"ambientBakeSpherePart":0.4,"ambientBakeOcclusionBrightness":0,"ambientBakeOcclusionContrast":0,"clusteredLightingEnabled":true,"lightingCells":[10,3,10],"lightingMaxLightsPerCell":255,"lightingCookieAtlasResolution":2048,"lightingShadowAtlasResolution":2048,"lightingShadowType":0,"lightingCookiesEnabled":false,"lightingAreaLightsEnabled":false,"lightingShadowsEnabled":true,"skyType":"infinite","skyMeshPosition":[0,0,0],"skyMeshRotation":[0,0,0],"skyMeshScale":[1,1,1],"skyCenter":[0,1,0]}},"entities":{"19cf7c05-7a64-4be2-8c47-9478853008bd":{"name":"Root","parent":null,"resource_id":"19cf7c05-7a64-4be2-8c47-9478853008bd","tags":[],"enabled":true,"components":{},"scale":[1,1,1],"position":[0,0,0],"rotation":[0,0,0],"children":["23c16a47-ffc1-4699-8066-0b1af9d2cb8e","84f77c6a-4a6c-49da-9315-2297ca019af9","06780a69-06e8-4de6-aadf-c74f631613bf"]},"23c16a47-ffc1-4699-8066-0b1af9d2cb8e":{"name":"Camera","parent":"19cf7c05-7a64-4be2-8c47-9478853008bd","resource_id":"23c16a47-ffc1-4699-8066-0b1af9d2cb8e","tags":[],"enabled":true,"components":{"camera":{"fov":45,"projection":0,"clearColor":[0.118,0.118,0.118,1],"clearColorBuffer":true,"clearDepthBuffer":true,"frustumCulling":true,"enabled":true,"orthoHeight":4,"farClip":1000,"nearClip":0.1,"priority":0,"rect":[0,0,1,1],"layers":[0,1,2,3,4]}},"scale":[1,1,1],"position":[0.5864187599011007,1.9630255606537395,5.256168365478516],"rotation":[0.5999998501146552,5.199999876916314,-1.0124509644555497e-9],"children":[]},"84f77c6a-4a6c-49da-9315-2297ca019af9":{"name":"Light","parent":"19cf7c05-7a64-4be2-8c47-9478853008bd","resource_id":"84f77c6a-4a6c-49da-9315-2297ca019af9","tags":[],"enabled":true,"components":{"light":{"enabled":true,"bake":false,"bakeNumSamples":1,"bakeArea":0,"bakeDir":true,"affectDynamic":true,"affectLightmapped":false,"isStatic":false,"color":[1,1,1],"intensity":1,"type":"directional","shadowDistance":16,"range":8,"innerConeAngle":40,"outerConeAngle":45,"shape":0,"falloffMode":0,"castShadows":true,"shadowUpdateMode":2,"shadowType":0,"shadowResolution":1024,"shadowBias":0.4,"normalOffsetBias":0.05,"vsmBlurMode":1,"vsmBlurSize":11,"vsmBias":0.01,"cookieAsset":null,"cookieIntensity":1,"cookieFalloff":true,"cookieChannel":"rgb","cookieAngle":0,"cookieScale":[1,1],"cookieOffset":[0,0],"layers":[0]}},"scale":[1,1,1],"position":[2,2,-2],"rotation":[45,135,0],"children":[]},"06780a69-06e8-4de6-aadf-c74f631613bf":{"name":"Sprite","tags":[],"enabled":true,"resource_id":"06780a69-06e8-4de6-aadf-c74f631613bf","parent":"19cf7c05-7a64-4be2-8c47-9478853008bd","children":["26d3129b-1c6c-48b5-934b-0f815fea70fe"],"position":[0,0,0],"rotation":[0,0,0],"scale":[1,1,1],"components":{"sprite":{"enabled":true,"type":"simple","width":1,"height":1,"color":[0.6235294117647059,0.13333333333333333,0.13333333333333333],"opacity":1,"flipX":false,"flipY":false,"spriteAsset":null,"frame":0,"speed":1,"batchGroupId":null,"layers":[0],"drawOrder":0,"autoPlayClip":null,"clips":{}},"script":{"enabled":true,"order":[],"scripts":{}}}},"26d3129b-1c6c-48b5-934b-0f815fea70fe":{"name":"2D Screen","tags":[],"enabled":true,"resource_id":"26d3129b-1c6c-48b5-934b-0f815fea70fe","parent":"06780a69-06e8-4de6-aadf-c74f631613bf","children":["026a7f0f-2b13-4004-9015-3799a7fc0a41"],"position":[0,1.9055191360860235,0],"rotation":[0,0,0],"scale":[1,1,1],"components":{"screen":{"enabled":true,"screenSpace":true,"scaleMode":"blend","scaleBlend":0.5,"resolution":[1280,720],"referenceResolution":[1280,720],"priority":0}}},"026a7f0f-2b13-4004-9015-3799a7fc0a41":{"name":"Button","tags":[],"enabled":true,"resource_id":"026a7f0f-2b13-4004-9015-3799a7fc0a41","parent":"26d3129b-1c6c-48b5-934b-0f815fea70fe","children":["dd52ebf3-c594-4f0b-b213-85f04f9cf214"],"position":[-16,16,0],"rotation":[0,0,0],"scale":[9.084047533047968,3.1712023288497964,6.880636243461431],"components":{"button":{"enabled":true,"active":true,"imageEntity":"026a7f0f-2b13-4004-9015-3799a7fc0a41","hitPadding":[0,0,0,0],"transitionMode":0,"hoverTint":[0.8627450980392157,0.7529411764705882,0.7529411764705882,1],"pressedTint":[1,1,1,1],"inactiveTint":[1,1,1,1],"fadeDuration":0,"hoverSpriteAsset":null,"hoverSpriteFrame":0,"pressedSpriteAsset":null,"pressedSpriteFrame":0,"inactiveSpriteAsset":null,"inactiveSpriteFrame":0,"hoverTextureAsset":null,"pressedTextureAsset":null,"inactiveTextureAsset":null},"element":{"enabled":true,"type":"image","anchor":[0.5,0.5,0.5,0.5],"pivot":[0.5,0.5],"text":"","key":null,"fontAsset":152024154,"fontSize":32,"minFontSize":8,"maxFontSize":32,"autoFitWidth":false,"autoFitHeight":false,"maxLines":null,"lineHeight":32,"wrapLines":true,"spacing":1,"color":[1,1,1],"opacity":1,"textureAsset":null,"spriteAsset":null,"spriteFrame":0,"pixelsPerUnit":null,"width":32,"height":32,"margin":[-32,0,0,-32],"alignment":[0.5,0.5],"outlineColor":[0,0,0,1],"outlineThickness":0,"shadowColor":[0,0,0,1],"shadowOffset":[0,0],"rect":[0,0,1,1],"materialAsset":null,"autoWidth":false,"autoHeight":false,"fitMode":"stretch","useInput":true,"batchGroupId":null,"mask":false,"layers":[4],"enableMarkup":false},"script":{"enabled":true,"order":["SceneChange"],"scripts":{"SceneChange":{"enabled":true,"attributes":{}}}}}},"dd52ebf3-c594-4f0b-b213-85f04f9cf214":{"name":"Text","tags":[],"enabled":true,"resource_id":"dd52ebf3-c594-4f0b-b213-85f04f9cf214","parent":"026a7f0f-2b13-4004-9015-3799a7fc0a41","children":[],"position":[15.999,15.996,0],"rotation":[0,0,0],"scale":[0.5767679207779856,1.3525777714379248,0.7413317334505326],"components":{"element":{"enabled":true,"type":"text","anchor":[0,0,1,1],"pivot":[0.5,0.5],"text":"START","key":null,"fontAsset":152024154,"fontSize":32,"minFontSize":8,"maxFontSize":32,"autoFitWidth":true,"autoFitHeight":true,"maxLines":null,"lineHeight":32,"wrapLines":true,"spacing":1.2,"color":[0.9294117647058824,0.6196078431372549,0.6196078431372549],"opacity":1,"textureAsset":null,"spriteAsset":null,"spriteFrame":0,"pixelsPerUnit":null,"width":32,"height":32,"margin":[-0.001,-0.004,0.001,0.004],"alignment":[0.5,0.5],"outlineColor":[0,0,0,1],"outlineThickness":0.295,"shadowColor":[0.9176470588235294,0.8549019607843137,0.8549019607843137,1],"shadowOffset":[0,0],"rect":[0,0,1,1],"materialAsset":null,"autoWidth":false,"autoHeight":false,"fitMode":"stretch","useInput":false,"batchGroupId":null,"mask":false,"layers":[4],"enableMarkup":false}}}},"created":"2023-09-29T10:07:05.142Z","id":1868667}